gaste_test/__init__.py
gaste_test/combined_pval.py
gaste_test/stratified_table2x2.py
gaste_test-0.1.3.dist-info/METADATA
gaste_test-0.1.3.dist-info/WHEEL
gaste_test-0.1.3.dist-info/top_level.txt
gaste_test-0.1.3.dist-info/RECORD
